EECS270_Lab3/fulladder.v
module full_adder(
    input  A,
    input  B,
    input  Cin,
    output Sum,
    output Cout
);

    assign Sum  = A ^ B ^ Cin;
    assign Cout = (A & B) | (A & Cin) | (B & Cin);

endmodule

EECS270_Lab3/rca.v
module ripple_adder_4(
    input  [3:0] A,
    input  [3:0] B,
    input        Cin,
    output [3:0] Sum,
    output       Overflow
);

    wire c1, c2, c3,c4;

    full_adder FA(
        .A(A[0]),
        .B(B[0]),
        .Cin(Cin),
        .Sum(Sum[0]),
        .Cout(c1)
    );

    full_adder FA1(
        .A(A[1]),
        .B(B[1]),
        .Cin(c1),
        .Sum(Sum[1]),
        .Cout(c2)
    );

    full_adder FA2(
        .A(A[2]),
        .B(B[2]),
        .Cin(c2),
        .Sum(Sum[2]),
        .Cout(c3)
    );

    full_adder FA3(
        .A(A[3]),
        .B(B[3]),
        .Cin(c3),
        .Sum(Sum[3]),
        .Cout(c4)
    );
    assign Overflow = (c3 ^ c4);

endmodule

EECS270_Lab3/alu.v
module alu4(
    input  [3:0] A,
    input  [3:0] B,
    input  [1:0] Op,

    output [3:0] Result,
    output Overflow
);

    // Arithmetic signals
    wire [3:0] B_sub;
    wire [3:0] AddSubResult;
    wire       AddSubOver;

    // Logic results
    wire [3:0] AndResult;
    wire [3:0] OrResult;
    wire [3:0] XorResult;

    // For subtraction:
    // Op=001 -> invert B and set Cin=1
    assign B_sub = (Op == 2'b01) ? ~B : B;

    ripple_adder_4 ADDER(
        .A(A),
        .B(B_sub),
        .Cin(Op == 2'b01),
        .Sum(AddSubResult),
        .Overflow(AddSubOver)
    );

    assign AndResult = A & B;
    assign OrResult  = A | B;
    assign XorResult = A ^ B;

    
    
    assign Result = (Op == 2'b00) ? AddSubResult :
                     (Op == 2'b01) ? AddSubResult :
                     (Op == 2'b10) ? AndResult    :
                     OrResult;

    // CarryOut only meaningful for add/sub; 0 otherwise
    assign Overflow = (Op == 2'b00 || Op == 2'b01) ? AddSubOver : 1'b0;

        

endmodule

EECS270_Lab3/lab3.v
module Lab3(
    input [17:0] SW,
    output [6:0] LEDR,
    output [3:0] LEDG,
    output [3:0] LEDY
);

    wire [3:0] A, B, Result;
    wire [1:0] Op;
    wire       Overflow;

    assign A = SW[3:0];
    assign B = SW[17:14];
    assign Op = SW[9:8];

    alu4 ALU(
        .A(A),
        .B(B),
        .Op(Op),
        .Result(Result),
        .Overflow(Overflow)
    );

    assign LEDG = A;
    assign LEDY = B;
    assign LEDR[3:0] = Result;
    assign LEDR[6:6] = Overflow;
    //assign LEDG = {3'b000, Overflow};
    //assign LEDY = {1'b0, Op};    


endmodule // Lab2

EECS270_Lab3/Lab3_tb.v
// File Name: Lab3_tb.v

`timescale 1 ns/1 ns
module TestBenchLab3();
    reg [17:0] SW;
    wire [6:0] LEDR;
    wire [3:0] LEDG;
    wire [3:0] LEDY;

    Lab3 L3(
        .SW(SW),
        .LEDR(LEDR),
        .LEDG(LEDG),
        .LEDY(LEDY)
    );

    initial begin
        $dumpvars(0, TestBenchLab3);

        // 00 A + B
        SW[3:0] = 4'b0001;
        SW[17:14] = 4'b0001;
        SW[9:8] = 2'b00;
        #10;

        SW[3:0] = 4'b1111;
        SW[17:14] = 4'b0000;
        SW[9:8] = 2'b00;
        #10;

        // 01 A - B
        SW[3:0] = 4'b0001;
        SW[17:14] = 4'b0001;
        SW[9:8] = 2'b01;
        #10;

        SW[3:0] = 4'b0000; // wrong
        SW[17:14] = 4'b1111;
        SW[9:8] = 2'b01;
        #10;

        SW[3:0] = 4'b0010; // wrong
        SW[17:14] = 4'b1000;
        SW[9:8] = 2'b01;
        #10;

        SW[3:0] = 4'b0110; // wrong
        SW[17:14] = 4'b1100;
        SW[9:8] = 2'b01;
        #10;

        // 10 A & B
        SW[3:0] = 4'b0001;
        SW[17:14] = 4'b0001;
        SW[9:8] = 2'b10;
        #10;

        SW[3:0] = 4'b0101;
        SW[17:14] = 4'b0101;
        SW[9:8] = 2'b10;
        #10;

        SW[3:0] = 4'b0000; // wrong
        SW[17:14] = 4'b1111;
        SW[9:8] = 2'b10;
        #10;

        SW[3:0] = 4'b0000;
        SW[17:14] = 4'b0000;
        SW[9:8] = 2'b10;
        #10;

        SW[3:0] = 4'b1111;
        SW[17:14] = 4'b1111;
        SW[9:8] = 2'b10;
        #10;

        // 11 A | B
        SW[3:0] = 4'b0001;
        SW[17:14] = 4'b0001;
        SW[9:8] = 2'b11;
        #10;

        SW[3:0] = 4'b0101; // wrong
        SW[17:14] = 4'b1010;
        SW[9:8] = 2'b11;
        #10;

        SW[3:0] = 4'b0000;
        SW[17:14] = 4'b0000;
        SW[9:8] = 2'b11;
        #10;

        SW[3:0] = 4'b1111;
        SW[17:14] = 4'b1111;
        SW[9:8] = 2'b11;
        #10;

        // assign A = SW[3:0];
        // assign B = SW[17:14];
        // assign Op = SW[9:8];
    end
endmodule

EECS270_Lab3/_build/default/Lab3_tb.vcd
$date
	Wed Sep 23 17:07:19 2026
$end
$version
	Icarus Verilog
$end
$timescale
	1ps
$end
$scope module TestBenchLab3 $end
$var wire 4 ! LEDY [3:0] $end
$var wire 7 " LEDR [6:0] $end
$var wire 4 # LEDG [3:0] $end
$var reg 18 $ SW [17:0] $end
$scope module L3 $end
$var wire 4 % LEDG [3:0] $end
$var wire 4 & LEDY [3:0] $end
$var wire 18 ' SW [17:0] $end
$var wire 4 ( Result [3:0] $end
$var wire 1 ) Overflow $end
$var wire 2 * Op [1:0] $end
$var wire 7 + LEDR [6:0] $end
$var wire 4 , B [3:0] $end
$var wire 4 - A [3:0] $end
$scope module ALU $end
$var wire 4 . A [3:0] $end
$var wire 4 / AndResult [3:0] $end
$var wire 4 0 B [3:0] $end
$var wire 2 1 Op [1:0] $end
$var wire 4 2 OrResult [3:0] $end
$var wire 4 3 XorResult [3:0] $end
$var wire 4 4 Result [3:0] $end
$var wire 1 ) Overflow $end
$var wire 4 5 B_sub [3:0] $end
$var wire 4 6 AddSubResult [3:0] $end
$var wire 1 7 AddSubOver $end
$scope module ADDER $end
$var wire 4 8 A [3:0] $end
$var wire 4 9 B [3:0] $end
$var wire 1 : Cin $end
$var wire 1 7 Overflow $end
$var wire 1 ; c4 $end
$var wire 1 < c3 $end
$var wire 1 = c2 $end
$var wire 1 > c1 $end
$var wire 4 ? Sum [3:0] $end
$scope module FA $end
$var wire 1 @ A $end
$var wire 1 A B $end
$var wire 1 : Cin $end
$var wire 1 > Cout $end
$var wire 1 B Sum $end
$upscope $end
$scope module FA1 $end
$var wire 1 C A $end
$var wire 1 D B $end
$var wire 1 > Cin $end
$var wire 1 = Cout $end
$var wire 1 E Sum $end
$upscope $end
$scope module FA2 $end
$var wire 1 F A $end
$var wire 1 G B $end
$var wire 1 = Cin $end
$var wire 1 < Cout $end
$var wire 1 H Sum $end
$upscope $end
$scope module FA3 $end
$var wire 1 I A $end
$var wire 1 J B $end
$var wire 1 < Cin $end
$var wire 1 ; Cout $end
$var wire 1 K Sum $end
$upscope $end
$upscope $end
$upscope $end
$upscope $end
$upscope $end
$enddefinitions $end
$comment Show the parameter values. $end
$dumpall
$end
#0
$dumpvars
0K
0J
0I
0H
0G
0F
1E
0D
0C
0B
1A
1@
b10 ?
1>
0=
0<
0;
0:
b1 9
b1 8
07
b10 6
b1 5
b10 4
b0 3
b1 2
b0 1
b1 0
b1 /
b1 .
b1 -
b1 ,
b0zz0010 +
b0 *
0)
b10 (
b1xxxx00xxxx0001 '
b1 &
b1 %
b1xxxx00xxxx0001 $
b1 #
b0zz0010 "
b1 !
$end
#10000
0;
0)
07
0<
b0zz1111 "
b0zz1111 +
0>
b1111 (
b1111 4
1B
0=
b1111 6
b1111 ?
1E
1H
1K
0A
b0 5
b0 9
b0 /
b1111 2
b1111 3
1C
1F
1I
b0 !
b0 &
b0 ,
b0 0
b1111 #
b1111 %
b1111 -
b1111 .
b1111 8
b0xxxx00xxxx1111 $
b0xxxx00xxxx1111 '
#20000
1;
0)
07
1<
b0zz0000 "
b0zz0000 +
1=
b0 (
b0 4
1>
0E
0H
0K
b0 6
b0 ?
0A
1D
1G
1J
0B
b1110 5
b1110 9
b1 /
b1 2
b0 3
0C
0F
0I
1:
b1 *
b1 1
b1 !
b1 &
b1 ,
b1 0
b1 #
b1 %
b1 -
b1 .
b1 8
b1xxxx01xxxx0001 $
b1xxxx01xxxx0001 '
#30000
b0zz0001 "
b0zz0001 +
b1 (
b1 4
0=
0H
0<
0K
0;
b1 6
b1 ?
0>
0D
0G
0J
1B
b0 5
b0 9
b0 /
b1111 2
b1111 3
0@
b1111 !
b1111 &
b1111 ,
b1111 0
b0 #
b0 %
b0 -
b0 .
b0 8
b1111xxxx01xxxx0000 $
b1111xxxx01xxxx0000 '
#40000
1)
1K
17
1<
b1zz1010 "
b1zz1010 +
1=
b1010 (
b1010 4
0B
1>
0H
b1010 6
b1010 ?
1A
1D
1G
1E
b111 5
b111 9
b1010 2
b1010 3
1C
b1000 !
b1000 &
b1000 ,
b1000 0
b10 #
b10 %
b10 -
b10 .
b10 8
b1000xxxx01xxxx0010 $
b1000xxxx01xxxx0010 '
#50000
b1zz1010 "
b1zz1010 +
b1010 (
b1010 4
b1010 6
b1010 ?
0G
0H
b11 5
b11 9
b100 /
b1110 2
1F
b1100 !
b1100 &
b1100 ,
b1100 0
b110 #
b110 %
b110 -
b110 .
b110 8
b1100xxxx01xxxx0110 $
b1100xxxx01xxxx0110 '
#60000
0K
07
0=
0<
b0zz0001 "
b0zz0001 +
0H
0D
b10 6
b10 ?
1>
b1 (
b1 4
0)
b1 5
b1 9
0B
b1 /
b1 2
b0 3
1@
0C
0F
0:
b10 *
b10 1
b1 !
b1 &
b1 ,
b1 0
b1 #
b1 %
b1 -
b1 .
b1 8
b1xxxx10xxxx0001 $
b1xxxx10xxxx0001 '
#70000
1K
17
1<
b0zz0101 "
b0zz0101 +
b101 (
b101 4
b1010 6
b1010 ?
0H
1G
b101 5
b101 9
b101 /
b101 2
1F
b101 !
b101 &
b101 ,
b101 0
b101 #
b101 %
b101 -
b101 .
b101 8
b101xxxx10xxxx0101 $
b101xxxx10xxxx0101 '
#80000
07
1K
b0zz0000 "
b0zz0000 +
0=
0;
b0 (
b0 4
0>
b1111 6
b1111 ?
0<
1B
1H
1D
1J
b1111 5
b1111 9
b0 /
b1111 2
b1111 3
0@
0F
b1111 !
b1111 &
b1111 ,
b1111 0
b0 #
b0 %
b0 -
b0 .
b0 8
b1111xxxx10xxxx0000 $
b1111xxxx10xxxx0000 '
#90000
b0 6
b0 ?
0B
0E
0H
0K
0A
0D
0G
0J
b0 2
b0 3
b0 5
b0 9
b0 !
b0 &
b0 ,
b0 0
b0xxxx10xxxx0000 $
b0xxxx10xxxx0000 '
#100000
1>
1=
1<
1;
b0zz1111 "
b0zz1111 +
b1111 (
b1111 4
b1110 6
b1110 ?
0B
1E
1H
1K
1A
1D
1G
1J
b1111 5
b1111 9
b1111 /
b1111 2
1@
1C
1F
1I
b1111 !
b1111 &
b1111 ,
b1111 0
b1111 #
b1111 %
b1111 -
b1111 .
b1111 8
b1111xxxx10xxxx1111 $
b1111xxxx10xxxx1111 '
#110000
b0zz0001 "
b0zz0001 +
0=
0<
b10 6
b10 ?
0;
b1 (
b1 4
1E
0H
0K
0D
0G
0J
b1 5
b1 9
b1 /
b1 2
0C
0F
0I
b11 *
b11 1
b1 !
b1 &
b1 ,
b1 0
b1 #
b1 %
b1 -
b1 .
b1 8
b1xxxx11xxxx0001 $
b1xxxx11xxxx0001 '
#120000
0;
07
0<
0>
b0zz1111 "
b0zz1111 +
1B
1E
0=
1K
b1111 (
b1111 4
b1111 6
b1111 ?
1H
0A
1D
1J
b1010 5
b1010 9
b0 /
b1111 2
b1111 3
1F
b1010 !
b1010 &
b1010 ,
b1010 0
b101 #
b101 %
b101 -
b101 .
b101 8
b1010xxxx11xxxx0101 $
b1010xxxx11xxxx0101 '
#130000
b0zz0000 "
b0zz0000 +
0E
0K
b0 (
b0 4
b0 6
b0 ?
0B
0H
0D
0J
b0 5
b0 9
b0 2
b0 3
0@
0F
b0 !
b0 &
b0 ,
b0 0
b0 #
b0 %
b0 -
b0 .
b0 8
b0xxxx11xxxx0000 $
b0xxxx11xxxx0000 '
#140000
1>
1=
1<
1;
b0zz1111 "
b0zz1111 +
b1111 (
b1111 4
b1110 6
b1110 ?
0B
1E
1H
1K
1A
1D
1G
1J
b1111 5
b1111 9
b1111 /
b1111 2
1@
1C
1F
1I
b1111 !
b1111 &
b1111 ,
b1111 0
b1111 #
b1111 %
b1111 -
b1111 .
b1111 8
b1111xxxx11xxxx1111 $
b1111xxxx11xxxx1111 '
