MuseumSecurity.v
module Museum_Security(
    input  D,
    input  V,
    input  M,
    input  H,
    output A
);




endmodule

lab2_tb.v
// File Name: TestBenchLab2.v (Museum Security)
`timescale 1 ns/1 ns	// time scale for simulation
module TestBenchLab2();
	reg [3:0] SW;
	wire [0:0] LEDR;

// Instantiate Museum_Security module
Museum_Security MS(.A(LEDR[0]), .H(SW[3]), .D(SW[2]), .M(SW[1]), .V(SW[0]));

// Test Procedure
	initial
	begin		
	// add a dumpvars clause here
	// your testcases go here
	$dumpvars(0, TestBenchLab2);

	SW = 4'b0000; #5;
	SW = 4'b0001; #5;
	SW = 4'b0010; #5;
	SW = 4'b0011; #5;
	SW = 4'b0100; #5;
	SW = 4'b0101; #5;
	SW = 4'b0110; #5;
	SW = 4'b0111; #5;

	SW = 4'b1000; #5;
	SW = 4'b1001; #5;
	SW = 4'b1010; #5;
	SW = 4'b1011; #5;
	SW = 4'b1100; #5;
	SW = 4'b1101; #5;
	SW = 4'b1110; #5;
	SW = 4'b1111; #5;

	end
endmodule // TestBenchLab2

_build/default/lab2_tb.vcd
$date
	Wed Sep 16 14:59:59 2026
$end
$version
	Icarus Verilog
$end
$timescale
	1ps
$end
$scope module TestBenchLab2 $end
$var wire 1 ! LEDR $end
$var reg 4 " SW [3:0] $end
$scope module MS $end
$var wire 1 ! A $end
$var wire 1 # D $end
$var wire 1 $ H $end
$var wire 1 % M $end
$var wire 1 & V $end
$upscope $end
$upscope $end
$enddefinitions $end
$comment Show the parameter values. $end
$dumpall
$end
#0
$dumpvars
0&
0%
0$
0#
b0 "
0!
$end
#5000
1&
b1 "
#10000
0&
1%
b10 "
#15000
1&
b11 "
#20000
1#
0&
0%
b100 "
#25000
1!
1&
b101 "
#30000
0!
0&
1%
b110 "
#35000
1!
1&
b111 "
#40000
0!
0#
0&
0%
1$
b1000 "
#45000
1!
1&
b1001 "
#50000
0&
1%
b1010 "
#55000
1&
b1011 "
#60000
1#
0&
0%
b1100 "
#65000
1&
b1101 "
#70000
0&
1%
b1110 "
#75000
1&
b1111 "
